kahoot/__init__.py
kahoot/client.py
kahoot/constants.py
kahoot/exceptions.py
kahoot/packets/__init__.py
kahoot/packets/impl/login.py
kahoot/packets/impl/respond.py
kahoot/packets/server/__init__.py
kahoot/packets/server/game_over.py
kahoot/packets/server/game_start.py
kahoot/packets/server/question_end.py
kahoot/packets/server/question_ready.py
kahoot/packets/server/question_start.py
kahoot/util/__init__.py
kahoot/util/general.py
kahoot/util/logger.py
kahoot/util/solver.py
kahoot-1.1.0.dist-info/LICENSE
kahoot-1.1.0.dist-info/METADATA
kahoot-1.1.0.dist-info/WHEEL
kahoot-1.1.0.dist-info/top_level.txt
kahoot-1.1.0.dist-info/RECORD
