Metadata-Version: 2.1
Name: kahoot
Version: 1.1.0
Summary: A Python package for interacting with the (private) Kahoot! Player API
Author-email: Vehbi <me@vehbi.me>
Project-URL: Homepage, https://github.com/vehbiu/kahoot-py
Keywords: kahoot,api,player
Classifier: Intended Audience :: Developers
Classifier: Programming Language :: Python
Classifier: Programming Language :: Python :: 3
Requires-Python: >=3.9
License-File: LICENSE
Requires-Dist: aiocometd-noloop==0.4.9
Requires-Dist: aiohappyeyeballs==2.4.3
Requires-Dist: aiohttp==3.10.10
Requires-Dist: aiosignal==1.3.1
Requires-Dist: anyio==4.6.0
Requires-Dist: attrs==24.2.0
Requires-Dist: certifi==2024.8.30
Requires-Dist: frozenlist==1.4.1
Requires-Dist: h11==0.14.0
Requires-Dist: httpcore==1.0.6
Requires-Dist: httpx==0.27.2
Requires-Dist: idna==3.10
Requires-Dist: multidict==6.1.0
Requires-Dist: propcache==0.2.0
Requires-Dist: py-mini-racer==0.6.0
Requires-Dist: sniffio==1.3.1
Requires-Dist: tasksio==0.0.0
Requires-Dist: yarl==1.14.0
